[
  {
    "ContainingType": "BookProject.Controllers.BookController",
    "Method": "GetAllBooks",
    "RelativePath": "api/Book",
    "HttpMethod": "GET",
    "IsController": true,
    "Order": 0,
    "Parameters": [],
    "ReturnTypes": [
      {
        "Type": "System.Collections.Generic.IEnumerable\u00601[[BookProject.Book, BookProject, Version=1.0.0.0, Culture=neutral, PublicKeyToken=null]]",
        "MediaTypes": [
          "text/plain",
          "application/json",
          "text/json"
        ],
        "StatusCode": 200
      }
    ],
    "EndpointName": "GetAllBooks"
  },
  {
    "ContainingType": "BookProject.Controllers.BookController",
    "Method": "AddBook",
    "RelativePath": "api/Book/add",
    "HttpMethod": "POST",
    "IsController": true,
    "Order": 0,
    "Parameters": [
      {
        "Name": "book",
        "Type": "BookProject.Book",
        "IsRequired": true
      }
    ],
    "ReturnTypes": [
      {
        "Type": "BookProject.Book",
        "MediaTypes": [
          "text/plain",
          "application/json",
          "text/json"
        ],
        "StatusCode": 200
      }
    ],
    "EndpointName": "AddBook"
  },
  {
    "ContainingType": "BookProject.Controllers.BookController",
    "Method": "GetBookByAuthor",
    "RelativePath": "api/Book/author/{author}",
    "HttpMethod": "GET",
    "IsController": true,
    "Order": 0,
    "Parameters": [
      {
        "Name": "author",
        "Type": "System.String",
        "IsRequired": true
      }
    ],
    "ReturnTypes": [
      {
        "Type": "System.Collections.Generic.IEnumerable\u00601[[BookProject.Book, BookProject, Version=1.0.0.0, Culture=neutral, PublicKeyToken=null]]",
        "MediaTypes": [
          "text/plain",
          "application/json",
          "text/json"
        ],
        "StatusCode": 200
      }
    ],
    "EndpointName": "GetBookByAuthor"
  },
  {
    "ContainingType": "BookProject.Controllers.BookController",
    "Method": "DeleteBook",
    "RelativePath": "api/Book/delete/isbn",
    "HttpMethod": "DELETE",
    "IsController": true,
    "Order": 0,
    "Parameters": [
      {
        "Name": "isbn",
        "Type": "System.String",
        "IsRequired": false
      }
    ],
    "ReturnTypes": [],
    "EndpointName": "DeleteBook"
  },
  {
    "ContainingType": "BookProject.Controllers.BookController",
    "Method": "GetBookByISBN",
    "RelativePath": "api/Book/isbn",
    "HttpMethod": "GET",
    "IsController": true,
    "Order": 0,
    "Parameters": [
      {
        "Name": "isbn",
        "Type": "System.String",
        "IsRequired": false
      }
    ],
    "ReturnTypes": [
      {
        "Type": "System.Collections.Generic.IEnumerable\u00601[[BookProject.Book, BookProject, Version=1.0.0.0, Culture=neutral, PublicKeyToken=null]]",
        "MediaTypes": [
          "text/plain",
          "application/json",
          "text/json"
        ],
        "StatusCode": 200
      }
    ],
    "EndpointName": "GetBookByISBN"
  },
  {
    "ContainingType": "BookProject.Controllers.BookController",
    "Method": "GetBookByTitle",
    "RelativePath": "api/Book/title/{title}",
    "HttpMethod": "GET",
    "IsController": true,
    "Order": 0,
    "Parameters": [
      {
        "Name": "title",
        "Type": "System.String",
        "IsRequired": true
      }
    ],
    "ReturnTypes": [
      {
        "Type": "BookProject.Book",
        "MediaTypes": [
          "text/plain",
          "application/json",
          "text/json"
        ],
        "StatusCode": 200
      }
    ],
    "EndpointName": "GetBookByTitle"
  }
]